.gitignore
README.rst
setup.py
collective/__init__.py
collective.js.fancybox.egg-info/PKG-INFO
collective.js.fancybox.egg-info/SOURCES.txt
collective.js.fancybox.egg-info/dependency_links.txt
collective.js.fancybox.egg-info/entry_points.txt
collective.js.fancybox.egg-info/namespace_packages.txt
collective.js.fancybox.egg-info/not-zip-safe
collective.js.fancybox.egg-info/requires.txt
collective.js.fancybox.egg-info/top_level.txt
collective/js/__init__.py
collective/js/fancybox/__init__.py
collective/js/fancybox/configure.zcml
collective/js/fancybox/upgrades.py
collective/js/fancybox/upgrades.zcml
collective/js/fancybox/profiles/default/cssregistry.xml
collective/js/fancybox/profiles/default/jsregistry.xml
collective/js/fancybox/profiles/default/metadata.xml
collective/js/fancybox/resources/UPDATING.txt
collective/js/fancybox/resources/blank.gif
collective/js/fancybox/resources/fancy_close.png
collective/js/fancybox/resources/fancy_loading.png
collective/js/fancybox/resources/fancy_nav_left.png
collective/js/fancybox/resources/fancy_nav_right.png
collective/js/fancybox/resources/fancy_shadow_e.png
collective/js/fancybox/resources/fancy_shadow_n.png
collective/js/fancybox/resources/fancy_shadow_ne.png
collective/js/fancybox/resources/fancy_shadow_nw.png
collective/js/fancybox/resources/fancy_shadow_s.png
collective/js/fancybox/resources/fancy_shadow_se.png
collective/js/fancybox/resources/fancy_shadow_sw.png
collective/js/fancybox/resources/fancy_shadow_w.png
collective/js/fancybox/resources/fancy_title_left.png
collective/js/fancybox/resources/fancy_title_main.png
collective/js/fancybox/resources/fancy_title_over.png
collective/js/fancybox/resources/fancy_title_right.png
collective/js/fancybox/resources/fancybox-x.png
collective/js/fancybox/resources/fancybox-y.png
collective/js/fancybox/resources/fancybox.png
collective/js/fancybox/resources/jquery.fancybox.css
collective/js/fancybox/resources/jquery.fancybox.js
collective/js/fancybox/resources/jquery.fancybox.pack.js
docs/HISTORY.txt
docs/INSTALL.txt
docs/LICENSE.GPL
docs/LICENSE.txt