Metadata-Version: 1.0
Name: collective.js.fancybox
Version: 1.3.4.1
Summary: Fancybox libraries for Plone
Home-page: http://pypi.python.org/pypi/collective.js.fancybox
Author: Radim Novotny
Author-email: novotny.radim@gmail.com
License: GPL
Keywords: fancybox plone jquery
Platform: UNKNOWN
Classifier: Framework :: Plone
Classifier: Framework :: Plone :: 4.0
Classifier: Framework :: Plone :: 4.1
Classifier: Programming Language :: Python
Classifier: Topic :: Software Development :: Libraries :: Python Modules
